<?xml version="1.0" encoding="UTF-8"?>

<pixls>

<pixl width="16" height="16" dir="0" id="0" name="noimg">
	<link href="http://www.missingimages.com/" />
<text>
This image has been deleted, fear the copytrolls.
</text>
</pixl>

<pixl width="16" height="16" dir="0" id="1" name="mario">
	<link href="http://www.nintendo.com/" />
<text>
Already converted countless times into cakes cookies and legos, now you too can memorize the correct combination of pixls to crotchet your own.
</text>
</pixl>

<pixl width="16" height="16" dir="0" id="2" name="ace">
	<link href="http://en.wikipedia.org/wiki/Ace_of_Spades" />
<text>
The elaborate ace of spades was once used as proof that the pack was genuine and tax had been paid.
</text>
</pixl>

<pixl width="16" height="16" dir="0" id="3" name="eeyore">
	<link href="http://en.wikipedia.org/wiki/Eeyore" />
<text>
The original gloomy goth.
</text>
</pixl>

<pixl width="16" height="16" dir="0" id="4" name="joystick">
	<link href="http://en.wikipedia.org/wiki/Kempston_Micro_Electronics" />
<text>
Before joypads had 20 buttons there where joysticks with one button. The kempston competition pro is a pure icon of 80s gaming.
</text>
</pixl>

<pixl width="16" height="16" dir="0" id="5" name="miner">
	<link href="http://en.wikipedia.org/wiki/Manic_Miner" />
<text>
Before monty there was manic and 2049er, this one is manic.
</text>
</pixl>

<pixl width="16" height="16" dir="0" id="6" name="e">
	<link href="http://en.wikipedia.org/wiki/E" />
<text>
This is an easy E, play fast to win.
</text>
</pixl>

<pixl width="16" height="16" dir="0" id="7" name="rgb_cube">
	<link href="http://en.wikipedia.org/wiki/Isometric_projection" />
<text>
An isometric cube made of red green and blue.
</text>
</pixl>

<pixl width="16" height="16" dir="0" id="8" name="melon_dezign">
	<link href="http://en.wikipedia.org/wiki/Melon_Dezign" />
<text>
A really butchered melon dezign logo, sorry but it is hard to fit it into 16x16.
</text>
</pixl>

<pixl width="16" height="16" dir="0" id="9" name="qbert">
	<link href="http://en.wikipedia.org/wiki/Q*bert" />
<text>
This ugly guy is Q*bert and he likes to swear.
</text>
</pixl>

<pixl width="16" height="16" dir="0" id="10" name="mochi">
	<link href="http://www.mochiads.com/games/" />
<text>
To build tools and services that support passionate content creators so that they can focus on what they love most: CREATIVITY.
</text>
</pixl>

<pixl width="16" height="16" dir="0" id="11" name="fuel">
	<link href="http://www.hobeka.com/" />
<text>
Some random images courtesy of Stoo Cambridge.
</text>
</pixl>

<pixl width="16" height="16" dir="0" id="12" name="galax1">
	<link href="http://www.hobeka.com/" />
<text>
Some random images courtesy of Stoo Cambridge.
</text>
</pixl>

<pixl width="16" height="16" dir="0" id="13" name="galax2">
	<link href="http://www.hobeka.com/" />
<text>
Some random images courtesy of Stoo Cambridge.
</text>
</pixl>

<pixl width="16" height="16" dir="0" id="14" name="key">
	<link href="http://www.hobeka.com/" />
<text>
Some random images courtesy of Stoo Cambridge.
</text>
</pixl>

<pixl width="16" height="16" dir="0" id="15" name="ship">
	<link href="http://www.hobeka.com/" />
<text>
Some random images courtesy of Stoo Cambridge.
</text>
</pixl>

<pixl width="16" height="16" dir="0" id="16" name="ship2">
	<link href="http://www.hobeka.com/" />
<text>
Some random images courtesy of Stoo Cambridge.
</text>
</pixl>

<pixl width="16" height="16" dir="0" id="17" name="like">
	<link href="http://like.4lfa.com/" />
<text>
Two meanings of the word like combined into one icon.
</text>
</pixl>

</pixls>
